biensoxe/__init__.py
biensoxe/core.py
biensoxe/django/__init__.py
biensoxe/django/fields.py
biensoxe/utils.py
biensoxe-0.8.5.dist-info/WHEEL
biensoxe-0.8.5.dist-info/METADATA
biensoxe-0.8.5.dist-info/RECORD
