Metadata-Version: 2.1
Name: biensoxe
Version: 0.8.5
Summary: Library to parse and validate Vietnamese vehicle plate
Home-page: https://github.com/sunshine-tech/BienSoXe
License: MIT
Author: Nguyễn Hồng Quân
Author-email: ng.hong.quan@gmail.com
Requires-Python: >=3.7,<4.0
Classifier: Development Status :: 4 - Beta
Classifier: Framework :: Django :: 2.2
Classifier: Intended Audience :: Developers
Classifier: Intended Audience :: Manufacturing
Classifier: License :: OSI Approved :: MIT License
Classifier: Natural Language :: Vietnamese
Classifier: Operating System :: OS Independent
Classifier: Programming Language :: Python :: 3
Classifier: Programming Language :: Python :: 3 :: Only
Classifier: Programming Language :: Python :: 3.7
Classifier: Programming Language :: Python :: 3.8
Classifier: Topic :: Home Automation
Classifier: Topic :: Software Development :: Embedded Systems
Classifier: Topic :: Software Development :: Internationalization
Classifier: Topic :: Software Development :: Libraries :: Python Modules
Classifier: Topic :: Software Development :: Localization
Requires-Dist: memoprop (>=0.2.0,<0.3.0)
Requires-Dist: pydantic (>=1.0,<2.0)
Project-URL: Repository, https://github.com/sunshine-tech/BienSoXe.git
